poetry_plugin_bump/plugin.py
poetry_plugin_bump-0.1.6.dist-info/METADATA
poetry_plugin_bump-0.1.6.dist-info/WHEEL
poetry_plugin_bump-0.1.6.dist-info/entry_points.txt
poetry_plugin_bump-0.1.6.dist-info/RECORD
