Metadata-Version: 2.1
Name: poetry-plugin-bump
Version: 0.1.6
Summary: poetry plugin to bump version
Home-page: https://github.com/trim21/poetry-plugin-bump
License: MIT
Author: trim21
Author-email: trim21me@gmail.com
Requires-Python: >=3.7,<4.0
Classifier: License :: OSI Approved :: MIT License
Classifier: Programming Language :: Python :: 3
Classifier: Programming Language :: Python :: 3.7
Classifier: Programming Language :: Python :: 3.8
Classifier: Programming Language :: Python :: 3.9
Classifier: Programming Language :: Python :: 3.10
Classifier: Programming Language :: Python :: 3.11
Classifier: Programming Language :: Python :: 3.12
Requires-Dist: poetry (>=1.5.0,<1.9.0)
Requires-Dist: semver (>=3.0.0,<4.0.0)
Project-URL: Repository, https://github.com/trim21/poetry-plugin-bump
